{
    "directed": true,
    "multigraph": false,
    "graph": [
        [
            "name",
            "Serial Arena"
        ],
        [
            "start_stations",
            [
                "S1"
            ]
        ],
        [
            "end_stations",
            [
                "S4"
            ]
        ],
        [
            "wip_limits",
            [
                12
            ]
        ],
        [
            "generation_time",
            73.59871292114258
        ]
    ],
    "nodes": [
        {
            "index": 0,
            "frequency": 9991,
            "buffer_capacity": 4,
            "machine_capacity": 1,
            "processing_time": {
                "mean": 86.8055555555559,
                "std": 39.92490700402081
            },
            "id": "S3"
        },
        {
            "index": 1,
            "frequency": 9994,
            "buffer_capacity": 0,
            "machine_capacity": 1,
            "processing_time": {
                "mean": 50.20443324937042,
                "std": 24.975929978455213
            },
            "id": "S1"
        },
        {
            "index": 2,
            "frequency": 9993,
            "buffer_capacity": 4,
            "machine_capacity": 2,
            "processing_time": {
                "mean": 150.42798690671046,
                "std": 75.13522901855576
            },
            "id": "S2"
        },
        {
            "index": 3,
            "frequency": 9995,
            "buffer_capacity": 6,
            "machine_capacity": 1,
            "processing_time": {
                "mean": 99.9514757378691,
                "std": 49.90518272615626
            },
            "id": "S4"
        }
    ],
    "adjacency": [
        [
            {
                "frequency": 9991,
                "routing_probability": 1.0,
                "transfer_time": {
                    "mean": 10.8,
                    "std": 3.3466401061363023
                },
                "id": "S4"
            }
        ],
        [
            {
                "frequency": 9994,
                "routing_probability": 1.0,
                "transfer_time": {
                    "mean": 10.064463111760405,
                    "std": 2.03172304774755
                },
                "id": "S2"
            }
        ],
        [
            {
                "frequency": 9993,
                "routing_probability": 1.0,
                "transfer_time": {
                    "mean": 10.076167076167074,
                    "std": 2.111800541875829
                },
                "id": "S3"
            }
        ],
        []
    ]
}